emulated_roku/__init__.py
emulated_roku-0.4.0.dist-info/licenses/LICENSE
emulated_roku-0.4.0.dist-info/METADATA
emulated_roku-0.4.0.dist-info/WHEEL
emulated_roku-0.4.0.dist-info/top_level.txt
emulated_roku-0.4.0.dist-info/zip-safe
emulated_roku-0.4.0.dist-info/RECORD
