Metadata-Version: 2.4
Name: emulated_roku
Version: 0.4.0
Summary: Library to emulate the Roku API for Home Assistant and other automation tools.
Home-page: https://gitlab.com/mindig.marton/emulated_roku
Download-URL: https://gitlab.com/mindig.marton/emulated_roku/repository/archive.zip?ref=0.4.0
Author: mindigmarton
Author-email: Marton Perei <marton@perei.me>
License: MIT
Project-URL: Homepage, https://github.com/martonperei/emulated_roku
Project-URL: Bug Tracker, https://github.com/martonperei/emulated_roku/issues
Keywords: roku,emulation,home-assistant,automation,aiohttp
Classifier: Intended Audience :: Developers
Classifier: License :: OSI Approved :: MIT License
Classifier: Programming Language :: Python :: 3
Requires-Python: >=3.8
License-File: LICENSE
Requires-Dist: aiohttp
Dynamic: author
Dynamic: download-url
Dynamic: home-page
Dynamic: license-file
